hcs_utils/__init__.py
hcs_utils/collections.py
hcs_utils/daemon.py
hcs_utils/itemstore.py
hcs_utils/json.py
hcs_utils/lock.py
hcs_utils/memoize.py
hcs_utils/path.py
hcs_utils/storage.py
hcs_utils/threading.py
hcs_utils/unittest.py
hcs_utils-2.1.0.dist-info/METADATA
hcs_utils-2.1.0.dist-info/WHEEL
hcs_utils-2.1.0.dist-info/RECORD
