Metadata-Version: 2.1
Name: hcs-utils
Version: 2.1.0
Summary: My personal library collecting some useful snippets.
Home-page: https://gitlab.com/hcs/hcs_utils
License: ISC License (ISCL)
Author: Christer Sjöholm
Author-email: 1357-hcs@users.noreply.gitlab.com
Requires-Python: >=3.12,<4.0
Classifier: Development Status :: 4 - Beta
Classifier: Intended Audience :: Developers
Classifier: License :: OSI Approved :: ISC License (ISCL)
Classifier: License :: Other/Proprietary License
Classifier: Operating System :: OS Independent
Classifier: Programming Language :: Python :: 3
Classifier: Programming Language :: Python :: 3.12
Classifier: Topic :: Software Development :: Libraries :: Python Modules
Project-URL: Repository, https://gitlab.com/hcs/hcs_utils
